README.md
setup.py
coerce/__init__.py
coerce.egg-info/PKG-INFO
coerce.egg-info/SOURCES.txt
coerce.egg-info/dependency_links.txt
coerce.egg-info/requires.txt
coerce.egg-info/top_level.txt