Metadata-Version: 2.1
Name: coerce
Version: 0.0.3
Summary: A type hint coercion decorator.
Home-page: https://github.com/almcc/coerce
Author: Alastair McClelland
Author-email: almcc.dev@gmail.com
License: UNKNOWN
Platform: UNKNOWN
Classifier: Programming Language :: Python :: 3.6
Classifier: Programming Language :: Python :: 3.7
Classifier: Programming Language :: Python :: 3.8
Classifier: License :: OSI Approved :: MIT License
Classifier: Operating System :: OS Independent
Provides-Extra: dev
